spacr/__init__.py
spacr/__main__.py
spacr/app_annotate.py
spacr/app_classify.py
spacr/app_make_masks.py
spacr/app_mask.py
spacr/app_measure.py
spacr/app_sequencing.py
spacr/app_umap.py
spacr/core.py
spacr/deep_spacr.py
spacr/gui.py
spacr/gui_core.py
spacr/gui_elements.py
spacr/gui_utils.py
spacr/io.py
spacr/logger.py
spacr/measure.py
spacr/ml.py
spacr/plot.py
spacr/sequencing.py
spacr/settings.py
spacr/sim.py
spacr/sp_stats.py
spacr/spacr_cellpose.py
spacr/spacrops.py
spacr/submodules.py
spacr/timelapse.py
spacr/toxo.py
spacr/utils.py
spacr/version.py
spacr/resources/data/lopit.csv
spacr/resources/data/toxoplasma_metadata.csv
spacr/resources/font/open_sans/OFL.txt
"spacr/resources/font/open_sans/OpenSans-Italic-VariableFont_wdth,wght.ttf"
"spacr/resources/font/open_sans/OpenSans-VariableFont_wdth,wght.ttf"
spacr/resources/font/open_sans/README.txt
spacr/resources/font/open_sans/static/OpenSans-Bold.ttf
spacr/resources/font/open_sans/static/OpenSans-BoldItalic.ttf
spacr/resources/font/open_sans/static/OpenSans-Italic.ttf
spacr/resources/font/open_sans/static/OpenSans-Light.ttf
spacr/resources/font/open_sans/static/OpenSans-LightItalic.ttf
spacr/resources/font/open_sans/static/OpenSans-Regular.ttf
spacr/resources/font/open_sans/static/OpenSans-SemiBold.ttf
spacr/resources/font/open_sans/static/OpenSans-SemiBoldItalic.ttf
spacr/resources/icons/abort.png
spacr/resources/icons/activation.png
spacr/resources/icons/annotate.png
spacr/resources/icons/cellpose_all.png
spacr/resources/icons/cellpose_masks.png
spacr/resources/icons/classify.png
spacr/resources/icons/convert.png
spacr/resources/icons/default.png
spacr/resources/icons/download.png
spacr/resources/icons/flow_chart_v3.png
spacr/resources/icons/logo_spacr.png
spacr/resources/icons/logo_spacr_v1.png
spacr/resources/icons/make_masks.png
spacr/resources/icons/map_barcodes.png
spacr/resources/icons/mask.png
spacr/resources/icons/measure.png
spacr/resources/icons/ml_analyze.png
spacr/resources/icons/plaque.png
spacr_nightly-1.2.1.dist-info/licenses/LICENSE
spacr_nightly-1.2.1.dist-info/METADATA
spacr_nightly-1.2.1.dist-info/WHEEL
spacr_nightly-1.2.1.dist-info/entry_points.txt
spacr_nightly-1.2.1.dist-info/top_level.txt
spacr_nightly-1.2.1.dist-info/RECORD
